airflow_supporter/__init__.py
airflow_supporter/dag/__init__.py
airflow_supporter/dag/check_off_dag.py
airflow_supporter/model/__init__.py
airflow_supporter/model/check_off_dag_model.py
airflow_supporter/model/restart_failed_dagrun_model.py
airflow_supporter/op/__init__.py
airflow_supporter/op/restart_failed_dagrun_op.py
airflow_supporter/op/restart_stucked_task_op.py
airflow_supporter/service/__init__.py
airflow_supporter/service/check_off_dag_op.py
airflow_supporter/service/handle_dag_op.py
airflow_supporter-1.0.0.dist-info/METADATA
airflow_supporter-1.0.0.dist-info/WHEEL
airflow_supporter-1.0.0.dist-info/RECORD
