Metadata-Version: 2.1
Name: airflow-supporter
Version: 1.0.0
Summary: Airflow Supporter
Home-page: https://github.com/ultimatelife/airflow-supporter
License: MIT
Keywords: apache-airflow,airflow,airflow-supporter
Author: Kunizno
Author-email: pykunzino@gmail.com
Maintainer: Kunizno
Maintainer-email: pykunzino@gmail.com
Requires-Python: >=3.10,<4.0
Classifier: Framework :: Apache Airflow
Classifier: Intended Audience :: Developers
Classifier: License :: OSI Approved :: MIT License
Classifier: Operating System :: OS Independent
Classifier: Programming Language :: Python :: 3
Classifier: Programming Language :: Python :: 3.10
Classifier: Programming Language :: Python :: 3.11
Classifier: Programming Language :: Python :: 3 :: Only
Classifier: Programming Language :: Python :: 3.7
Classifier: Programming Language :: Python :: 3.8
Classifier: Programming Language :: Python :: 3.9
Requires-Dist: apache-airflow (>=2.2.2,<3.0.0)
Requires-Dist: pydantic (>=1.9.2,<2.0.0)
Project-URL: Repository, https://github.com/ultimatelife/airflow-supporter
